rfm69/__init__.py
rfm69/configuration.py
rfm69/constants.py
rfm69/register_value.py
rfm69/rfm69.py
rfm69-0.3.dist-info/DESCRIPTION.rst
rfm69-0.3.dist-info/METADATA
rfm69-0.3.dist-info/RECORD
rfm69-0.3.dist-info/WHEEL
rfm69-0.3.dist-info/metadata.json
rfm69-0.3.dist-info/top_level.txt
